requirements.txt
model_zoo/__init__.py
model_zoo/__version__.py
model_zoo/callbacks.py
model_zoo/evaluater.py
model_zoo/exceptions.py
model_zoo/flags.py
model_zoo/framework.py
model_zoo/inferer.py
model_zoo/logger.py
model_zoo/model.py
model_zoo/preprocess.py
model_zoo/trainer.py
model_zoo/utils.py
model_zoo-0.4.1.dist-info/LICENSE
model_zoo-0.4.1.dist-info/METADATA
model_zoo-0.4.1.dist-info/WHEEL
model_zoo-0.4.1.dist-info/top_level.txt
model_zoo-0.4.1.dist-info/RECORD
