Metadata-Version: 2.1
Name: model-zoo
Version: 0.4.1
Summary: A framework to help you build model much more easily.
Home-page: https://github.com/ModelZoo/ModelZoo
Author: Germey
Author-email: cqc@cuiqingcai.com
License: MIT
Platform: UNKNOWN
Classifier: License :: OSI Approved :: MIT License
Classifier: Programming Language :: Python :: 3.5
Classifier: Programming Language :: Python :: 3.6
Classifier: Programming Language :: Python :: 3.7
Classifier: Programming Language :: Python :: Implementation :: CPython
Classifier: Programming Language :: Python :: Implementation :: PyPy
Requires-Python: >=3.5.0
Requires-Dist: absl-py (>=0.5.0)
Requires-Dist: astor (>=0.7.1)
Requires-Dist: cycler (>=0.10.0)
Requires-Dist: h5py (>=2.8.0)
Requires-Dist: kiwisolver (>=1.0.1)
Requires-Dist: matplotlib (>=3.0.0)
Requires-Dist: numpy (>=1.15.2)
Requires-Dist: pandas (>=0.23.4)
Requires-Dist: protobuf (>=3.6.1)
Requires-Dist: pyparsing (>=2.2.2)
Requires-Dist: scipy (>=1.1.0)
Requires-Dist: six (>=1.11.0)
Requires-Dist: sklearn
Requires-Dist: tensorflow (>=2.0.0)
Requires-Dist: termcolor (>=1.1.0)
Requires-Dist: werkzeug (>=0.15.3)
Requires-Dist: loguru (>=0.3.2)
Requires-Dist: pyyaml (>=5.1.2)
